pywssocks/__init__.py
pywssocks/__main__.py
pywssocks/cli.py
pywssocks/client.py
pywssocks/common.py
pywssocks/message.py
pywssocks/relay.py
pywssocks/server.py
pywssocks-1.5.1.dist-info/licenses/LICENSE
tests/__init__.py
tests/conftest.py
tests/test_cli.py
tests/test_common.py
tests/test_edge_cases.py
tests/test_lib.py
tests/test_message.py
tests/test_upstream_proxy.py
tests/utils.py
pywssocks-1.5.1.dist-info/METADATA
pywssocks-1.5.1.dist-info/WHEEL
pywssocks-1.5.1.dist-info/entry_points.txt
pywssocks-1.5.1.dist-info/top_level.txt
pywssocks-1.5.1.dist-info/RECORD
