Metadata-Version: 2.4
Name: pywssocks
Version: 1.5.1
Summary: A forward and reverse socks over websocket server and client implementation in Python.
Author-email: jackzzs <jackzzs@outlook.com>
Project-URL: Homepage, https://github.com/linksocks/pywssocks
Classifier: Programming Language :: Python :: 3
Classifier: License :: OSI Approved :: MIT License
Classifier: Operating System :: OS Independent
Requires-Python: >=3.8
License-File: LICENSE
Requires-Dist: websockets>=13.1
Requires-Dist: click
Provides-Extra: dev
Requires-Dist: pytest; extra == "dev"
Requires-Dist: pytest-xdist; extra == "dev"
Requires-Dist: httpx[socks]; extra == "dev"
Requires-Dist: requests[socks]; extra == "dev"
Requires-Dist: python-socks[asyncio]; extra == "dev"
Requires-Dist: bump2version; extra == "dev"
Requires-Dist: debugpy; extra == "dev"
Requires-Dist: mkdocs-material; extra == "dev"
Requires-Dist: mkdocstrings[python]>=0.18; extra == "dev"
Requires-Dist: pytest-cov; extra == "dev"
Requires-Dist: black; extra == "dev"
Dynamic: license-file
